setup.py
deezeridu/__init__.py
deezeridu/api.py
deezeridu/download.py
deezeridu/download_utils.py
deezeridu/exceptions.py
deezeridu/gateway.py
deezeridu/settings.py
deezeridu/taggers.py
deezeridu/utils.py
deezeridu.egg-info/PKG-INFO
deezeridu.egg-info/SOURCES.txt
deezeridu.egg-info/dependency_links.txt
deezeridu.egg-info/requires.txt
deezeridu.egg-info/top_level.txt
deezeridu/models/__init__.py
deezeridu/models/album.py
deezeridu/models/playlist.py
deezeridu/models/preferences.py
deezeridu/models/track.py