Metadata-Version: 2.1
Name: deezeridu
Version: 0.0.2
Summary: Downloads songs, albums or playlists from deezer
Home-page: https://github.com/OpenJarbas/deezeridu
Author: An0nimia
License: CC BY-NC-SA 4.0
Platform: UNKNOWN
Requires-Python: >=3.8
